fifo1.v
// counter.v

`timescale 1ns / 1ps

module counter(
  input clk,
  input clr,
  output [3:0] q
);
reg [3:0] q_temp;
assign q = q_temp;
always @(posedge clk or negedge clr)
  if (~clr)
    q_temp <= 4'b0000;
  else if (q_temp == 4'b1001)
    q_temp <= 4'b0000;
  else
    q_temp <= q_temp + 1'b1;
endmodule


module counter_tb;
reg clr;
reg clk;
wire [3:0] q;

counter tb(
  .clr(clr),
  .clk(clk),
  .q(q)
);

initial begin
  $dumpfile("run.vcd");
  $dumpvars;
  clr = 0;
  clk = 0;
  #40
  clr = 1;
end

always #10 clk = ~clk;

initial #500 $finish;
endmodule

run.vcd
$date
	Wed Jul 22 19:09:34 2020
$end
$version
	Icarus Verilog
$end
$timescale
	1ps
$end
$scope module counter_tb $end
$var wire 4 ! q [3:0] $end
$var reg 1 " clk $end
$var reg 1 # clr $end
$scope module tb $end
$var wire 1 " clk $end
$var wire 1 # clr $end
$var wire 4 $ q [3:0] $end
$var reg 4 % q_temp [3:0] $end
$upscope $end
$upscope $end
$enddefinitions $end
#0
$dumpvars
b0 %
b0 $
0#
0"
b0 !
$end
#10000
1"
#20000
0"
#30000
1"
#40000
0"
1#
#50000
b1 !
b1 $
b1 %
1"
#60000
0"
#70000
b10 !
b10 $
b10 %
1"
#80000
0"
#90000
b11 !
b11 $
b11 %
1"
#100000
0"
#110000
b100 !
b100 $
b100 %
1"
#120000
0"
#130000
b101 !
b101 $
b101 %
1"
#140000
0"
#150000
b110 !
b110 $
b110 %
1"
#160000
0"
#170000
b111 !
b111 $
b111 %
1"
#180000
0"
#190000
b1000 !
b1000 $
b1000 %
1"
#200000
0"
#210000
b1001 !
b1001 $
b1001 %
1"
#220000
0"
#230000
b0 !
b0 $
b0 %
1"
#240000
0"
#250000
b1 !
b1 $
b1 %
1"
#260000
0"
#270000
b10 !
b10 $
b10 %
1"
#280000
0"
#290000
b11 !
b11 $
b11 %
1"
#300000
0"
#310000
b100 !
b100 $
b100 %
1"
#320000
0"
#330000
b101 !
b101 $
b101 %
1"
#340000
0"
#350000
b110 !
b110 $
b110 %
1"
#360000
0"
#370000
b111 !
b111 $
b111 %
1"
#380000
0"
#390000
b1000 !
b1000 $
b1000 %
1"
#400000
0"
#410000
b1001 !
b1001 $
b1001 %
1"
#420000
0"
#430000
b0 !
b0 $
b0 %
1"
#440000
0"
#450000
b1 !
b1 $
b1 %
1"
#460000
0"
#470000
b10 !
b10 $
b10 %
1"
#480000
0"
#490000
b11 !
b11 $
b11 %
1"
